nozomi_cli/__init__.py
nozomi_cli/api.py
nozomi_cli/auth.py
nozomi_cli/banner.py
nozomi_cli/config.py
nozomi_cli/main.py
nozomi_cli/output.py
nozomi_cli/terminal.py
nozomi_cli-0.0.2.dist-info/METADATA
nozomi_cli-0.0.2.dist-info/WHEEL
nozomi_cli-0.0.2.dist-info/entry_points.txt
nozomi_cli-0.0.2.dist-info/licenses/LICENSE
nozomi_cli-0.0.2.dist-info/RECORD
