Metadata-Version: 2.4
Name: nozomi-cli
Version: 0.0.2
Summary: Nozomi CLI - Remote workspace platform for AI coding agents
Project-URL: Homepage, https://nozomi.sh
Project-URL: Documentation, https://nozomi.sh/docs
Author-email: Roshan Pawar <roshan@r614.dev>
License-Expression: MIT
License-File: LICENSE
Keywords: ai,cli,coding,remote,terminal,workspace
Classifier: Development Status :: 3 - Alpha
Classifier: Environment :: Console
Classifier: Intended Audience :: Developers
Classifier: License :: OSI Approved :: MIT License
Classifier: Operating System :: OS Independent
Classifier: Programming Language :: Python :: 3
Classifier: Programming Language :: Python :: 3.11
Classifier: Programming Language :: Python :: 3.12
Classifier: Programming Language :: Python :: 3.13
Classifier: Topic :: Software Development
Classifier: Topic :: Terminals
Requires-Python: >=3.11
Requires-Dist: click>=8.1.0
Requires-Dist: httpx>=0.27.0
Requires-Dist: keyring>=25.0.0
Requires-Dist: packaging>=23.0
Requires-Dist: questionary>=2.0.0
Requires-Dist: rich>=13.0.0
